{
  "accounts": "Daftar Rekening",
  "addresses": "Daftar Alamat",
  "auction_room": "Ruang Lelang",
  "banks": "Daftar Bank",
  "create_account": "Buat Rekening",
  "create_address": "Buat Alamat",
  "create_product": "Buat Produk",
  "edit_account": "Ubah Rekening",
  "edit_address": "Ubah Alamat",
  "edit_product": "Ubah Produk",
  "home": "Beranda",
  "invoice_detail": "Detail Faktur",
  "invoices": "Daftar Faktur",
  "joined": "Mengikuti",
  "product_detail": "Detail Produk",
  "profile": "Profil",
  "user_products": "Daftar Produk Pengguna"
}
